gdal_installer/__init__.py
gdal_installer/cli.py
gdal_installer/install-gdal.py
gdal_installer-1.0.1.dist-info/LICENSE.md
gdal_installer-1.0.1.dist-info/METADATA
gdal_installer-1.0.1.dist-info/WHEEL
gdal_installer-1.0.1.dist-info/entry_points.txt
gdal_installer-1.0.1.dist-info/top_level.txt
gdal_installer-1.0.1.dist-info/RECORD
