Metadata-Version: 2.1
Name: gdal-installer
Version: 1.0.1
Summary: A tool to install GDAL wheels on Windows and wrapper for pip on Unix
Home-page: https://github.com/celray/python-gdal-installer
Author: Celray James CHAWANDA
Author-email: celray.chawanda@outlook.com
License: MIT
Keywords: gdal,gis,installer
Classifier: Programming Language :: Python :: 3
Classifier: License :: OSI Approved :: MIT License
Classifier: Operating System :: OS Independent
Requires-Python: >=3.10
License-File: LICENSE.md
Requires-Dist: requests>=2.25.0
Requires-Dist: tqdm>=4.65.0
